{
  "schemaVersion": 1,
  "id": "autoinventorytotem",
  "version": "1.0.0",
  "name": "AutoInventoryTotem",
  "description": "Keeps Totems of Undying in offhand and chosen hotbar slot.",
  "authors": ["REXYKILLER441"],
  "license": "MIT",
  "environment": "client",
  "entrypoints": {
    "client": [
      "com.autoinventorytotem.AutoInventoryTotem"
    ]
  },
  "depends": {
    "fabricloader": ">=0.15.11",
    "fabric": "*",
    "cloth-config2": "*",
    "modmenu": "*",
    "autoconfig1": "*"
  }
}
